PyMapRetinotopic-1.0.0.dist-info/DESCRIPTION.rst
PyMapRetinotopic-1.0.0.dist-info/METADATA
PyMapRetinotopic-1.0.0.dist-info/RECORD
PyMapRetinotopic-1.0.0.dist-info/WHEEL
PyMapRetinotopic-1.0.0.dist-info/metadata.json
PyMapRetinotopic-1.0.0.dist-info/top_level.txt
retinotopic_mapping/DisplayStimulus.py
retinotopic_mapping/MonitorSetup.py
retinotopic_mapping/RetinotopicMapping.py
retinotopic_mapping/StimulusRoutines.py
retinotopic_mapping/__init__.py
retinotopic_mapping/animation.py
retinotopic_mapping/for_debugging.py
retinotopic_mapping/test.py
retinotopic_mapping/tools/FileTools.py
retinotopic_mapping/tools/ImageAnalysis.py
retinotopic_mapping/tools/PlottingTools.py
retinotopic_mapping/tools/__init__.py
retinotopic_mapping/tools/IO/__init__.py
retinotopic_mapping/tools/IO/nidaq.py
